tsclasses/__init__.py
tsclasses/validate.py
tsclasses-0.0.2.dist-info/METADATA
tsclasses-0.0.2.dist-info/WHEEL
tsclasses-0.0.2.dist-info/licenses/LICENSE
tsclasses-0.0.2.dist-info/RECORD
