Metadata-Version: 2.1
Name: TSclasses
Version: 0.0.2
Summary: Simple Class Attribute Type Validation
Project-URL: Homepage, https://github.com/gon555551/tsclasses
Project-URL: Issues, https://github.com/gon555551/tsclasses/issues
License-File: LICENSE
Classifier: License :: OSI Approved :: MIT License
Classifier: Operating System :: OS Independent
Classifier: Programming Language :: Python :: 3
Requires-Python: >=3.8
